setup.py
brynq_sdk_task_scheduler/__init__.py
brynq_sdk_task_scheduler/task_scheduler.py
brynq_sdk_task_scheduler.egg-info/PKG-INFO
brynq_sdk_task_scheduler.egg-info/SOURCES.txt
brynq_sdk_task_scheduler.egg-info/dependency_links.txt
brynq_sdk_task_scheduler.egg-info/not-zip-safe
brynq_sdk_task_scheduler.egg-info/requires.txt
brynq_sdk_task_scheduler.egg-info/top_level.txt