Metadata-Version: 1.0
Name: brynq-sdk-task-scheduler
Version: 4.0.1
Summary: Code to execute tasks in BrynQ.com with the task scheduler
Home-page: UNKNOWN
Author: BrynQ
Author-email: support@brynq.com
License: BrynQ License
Platform: UNKNOWN
